[
  {
    "line": 1,
    "elements": [
      {
        "line": 26,
        "name": "Generating order id",
        "description": "",
        "id": "generating-10-order-id-from-adactin-hotel-page;generating-order-id;;2",
        "type": "scenario",
        "keyword": "Scenario Outline",
        "steps": [
          {
            "result": {
              "duration": 17579246700,
              "status": "passed"
            },
            "line": 5,
            "name": "user is on adactin application on chrome browser",
            "match": {
              "location": "StepDef.user_is_on_adactin_application_on_chrome_browser()"
            },
            "keyword": "Given "
          },
          {
            "result": {
              "duration": 512348100,
              "status": "passed"
            },
            "line": 7,
            "name": "user enter \"mohankumar08\" and \"Mohan@123\"",
            "match": {
              "arguments": [
                {
                  "val": "\"mohankumar08\"",
                  "offset": 11
                },
                {
                  "val": "\"Mohan@123\"",
                  "offset": 30
                }
              ],
              "location": "StepDef.user_enter_and(String,String)"
            },
            "keyword": "When "
          },
          {
            "result": {
              "duration": 2244519500,
              "status": "passed"
            },
            "line": 9,
            "name": "user should click login button",
            "match": {
              "location": "StepDef.user_should_click_login_button()"
            },
            "keyword": "And "
          },
          {
            "result": {
              "duration": 1352562300,
              "status": "passed"
            },
            "line": 11,
            "name": "user select \"Sydney\", \"Hotel Sunshine\", \"Deluxe\", \"1\", \"13/05/2022\", \"15/05/2022\", \"2\" and \"1\"",
            "match": {
              "arguments": [
                {
                  "val": "\"Sydney\"",
                  "offset": 12
                },
                {
                  "val": "\"Hotel Sunshine\"",
                  "offset": 22
                },
                {
                  "val": "\"Deluxe\"",
                  "offset": 40
                },
                {
                  "val": "\"1\"",
                  "offset": 50
                },
                {
                  "val": "\"13/05/2022\"",
                  "offset": 55
                },
                {
                  "val": "\"15/05/2022\"",
                  "offset": 69
                },
                {
                  "val": "\"2\"",
                  "offset": 83
                },
                {
                  "val": "\"1\"",
                  "offset": 91
                }
              ],
              "location": "StepDef.user_select_and(String,String,String,String,String,String,String,String)"
            },
            "keyword": "When "
          },
          {
            "result": {
              "duration": 876623700,
              "status": "passed"
            },
            "line": 13,
            "name": "user should click search button",
            "match": {
              "location": "StepDef.user_should_click_search_button()"
            },
            "keyword": "And "
          },
          {
            "result": {
              "duration": 1002399900,
              "status": "passed"
            },
            "line": 15,
            "name": "user select hotel and click continue for booking",
            "match": {
              "location": "StepDef.user_select_hotel_and_click_continue_for_booking()"
            },
            "keyword": "When "
          },
          {
            "result": {
              "duration": 1646814900,
              "status": "passed"
            },
            "line": 17,
            "name": "user enter \"Mohan\", \"Kumar\", \"Chennai,Tamilnadu\", \"4563984512988765\",  \"VISA\", \"8\", \"2022\", \"240\"",
            "match": {
              "arguments": [
                {
                  "val": "\"Mohan\"",
                  "offset": 11
                },
                {
                  "val": "\"Kumar\"",
                  "offset": 20
                },
                {
                  "val": "\"Chennai,Tamilnadu\"",
                  "offset": 29
                },
                {
                  "val": "\"4563984512988765\"",
                  "offset": 50
                },
                {
                  "val": "\"VISA\"",
                  "offset": 71
                },
                {
                  "val": "\"8\"",
                  "offset": 79
                },
                {
                  "val": "\"2022\"",
                  "offset": 84
                },
                {
                  "val": "\"240\"",
                  "offset": 92
                }
              ],
              "location": "StepDef.user_enter(String,String,String,String,String,String,String,String)"
            },
            "keyword": "When "
          },
          {
            "result": {
              "duration": 126202200,
              "status": "passed"
            },
            "line": 19,
            "name": "user click on continue for generating order id",
            "match": {
              "location": "StepDef.user_click_on_continue_for_generating_order_id()"
            },
            "keyword": "And "
          },
          {
            "result": {
              "duration": 5939997000,
              "status": "passed"
            },
            "line": 21,
            "name": "user print order id into console",
            "match": {
              "location": "StepDef.user_print_order_id_into_console()"
            },
            "keyword": "And "
          }
        ]
      },
      {
        "line": 28,
        "name": "Generating order id",
        "description": "",
        "id": "generating-10-order-id-from-adactin-hotel-page;generating-order-id;;3",
        "type": "scenario",
        "keyword": "Scenario Outline",
        "steps": [
          {
            "result": {
              "duration": 7888172300,
              "status": "passed"
            },
            "line": 5,
            "name": "user is on adactin application on chrome browser",
            "match": {
              "location": "StepDef.user_is_on_adactin_application_on_chrome_browser()"
            },
            "keyword": "Given "
          },
          {
            "result": {
              "duration": 559026800,
              "status": "passed"
            },
            "line": 7,
            "name": "user enter \"mohankumar08\" and \"Mohan@123\"",
            "match": {
              "arguments": [
                {
                  "val": "\"mohankumar08\"",
                  "offset": 11
                },
                {
                  "val": "\"Mohan@123\"",
                  "offset": 30
                }
              ],
              "location": "StepDef.user_enter_and(String,String)"
            },
            "keyword": "When "
          },
          {
            "result": {
              "duration": 2245780100,
              "status": "passed"
            },
            "line": 9,
            "name": "user should click login button",
            "match": {
              "location": "StepDef.user_should_click_login_button()"
            },
            "keyword": "And "
          },
          {
            "result": {
              "duration": 1107472900,
              "status": "passed"
            },
            "line": 11,
            "name": "user select \"Melbourne\", \"Hotel Creek\", \"Super Deluxe\", \"2\", \"10/05/2022\", \"12/05/2022\", \"2\" and \"1\"",
            "match": {
              "arguments": [
                {
                  "val": "\"Melbourne\"",
                  "offset": 12
                },
                {
                  "val": "\"Hotel Creek\"",
                  "offset": 25
                },
                {
                  "val": "\"Super Deluxe\"",
                  "offset": 40
                },
                {
                  "val": "\"2\"",
                  "offset": 56
                },
                {
                  "val": "\"10/05/2022\"",
                  "offset": 61
                },
                {
                  "val": "\"12/05/2022\"",
                  "offset": 75
                },
                {
                  "val": "\"2\"",
                  "offset": 89
                },
                {
                  "val": "\"1\"",
                  "offset": 97
                }
              ],
              "location": "StepDef.user_select_and(String,String,String,String,String,String,String,String)"
            },
            "keyword": "When "
          },
          {
            "result": {
              "duration": 767963100,
              "status": "passed"
            },
            "line": 13,
            "name": "user should click search button",
            "match": {
              "location": "StepDef.user_should_click_search_button()"
            },
            "keyword": "And "
          },
          {
            "result": {
              "duration": 979209300,
              "status": "passed"
            },
            "line": 15,
            "name": "user select hotel and click continue for booking",
            "match": {
              "location": "StepDef.user_select_hotel_and_click_continue_for_booking()"
            },
            "keyword": "When "
          },
          {
            "result": {
              "duration": 1281353200,
              "status": "passed"
            },
            "line": 17,
            "name": "user enter \"Mohan\", \"Kumar\", \"Chennai,Tamilnadu\", \"4563984512988765\",  \"VISA\", \"8\", \"2022\", \"240\"",
            "match": {
              "arguments": [
                {
                  "val": "\"Mohan\"",
                  "offset": 11
                },
                {
                  "val": "\"Kumar\"",
                  "offset": 20
                },
                {
                  "val": "\"Chennai,Tamilnadu\"",
                  "offset": 29
                },
                {
                  "val": "\"4563984512988765\"",
                  "offset": 50
                },
                {
                  "val": "\"VISA\"",
                  "offset": 71
                },
                {
                  "val": "\"8\"",
                  "offset": 79
                },
                {
                  "val": "\"2022\"",
                  "offset": 84
                },
                {
                  "val": "\"240\"",
                  "offset": 92
                }
              ],
              "location": "StepDef.user_enter(String,String,String,String,String,String,String,String)"
            },
            "keyword": "When "
          },
          {
            "result": {
              "duration": 92812100,
              "status": "passed"
            },
            "line": 19,
            "name": "user click on continue for generating order id",
            "match": {
              "location": "StepDef.user_click_on_continue_for_generating_order_id()"
            },
            "keyword": "And "
          },
          {
            "result": {
              "duration": 6027801700,
              "status": "passed"
            },
            "line": 21,
            "name": "user print order id into console",
            "match": {
              "location": "StepDef.user_print_order_id_into_console()"
            },
            "keyword": "And "
          }
        ]
      },
      {
        "line": 30,
        "name": "Generating order id",
        "description": "",
        "id": "generating-10-order-id-from-adactin-hotel-page;generating-order-id;;4",
        "type": "scenario",
        "keyword": "Scenario Outline",
        "steps": [
          {
            "result": {
              "duration": 24569681500,
              "status": "passed"
            },
            "line": 5,
            "name": "user is on adactin application on chrome browser",
            "match": {
              "location": "StepDef.user_is_on_adactin_application_on_chrome_browser()"
            },
            "keyword": "Given "
          },
          {
            "result": {
              "duration": 419359500,
              "status": "passed"
            },
            "line": 7,
            "name": "user enter \"mohankumar08\" and \"Mohan@123\"",
            "match": {
              "arguments": [
                {
                  "val": "\"mohankumar08\"",
                  "offset": 11
                },
                {
                  "val": "\"Mohan@123\"",
                  "offset": 30
                }
              ],
              "location": "StepDef.user_enter_and(String,String)"
            },
            "keyword": "When "
          },
          {
            "result": {
              "duration": 2360799300,
              "status": "passed"
            },
            "line": 9,
            "name": "user should click login button",
            "match": {
              "location": "StepDef.user_should_click_login_button()"
            },
            "keyword": "And "
          },
          {
            "result": {
              "duration": 1396100300,
              "status": "passed"
            },
            "line": 11,
            "name": "user select \"Brisbane\", \"Hotel Hervey\", \"Double\", \"3\", \"21/05/2022\", \"28/05/2022\", \"4\" and \"1\"",
            "match": {
              "arguments": [
                {
                  "val": "\"Brisbane\"",
                  "offset": 12
                },
                {
                  "val": "\"Hotel Hervey\"",
                  "offset": 24
                },
                {
                  "val": "\"Double\"",
                  "offset": 40
                },
                {
                  "val": "\"3\"",
                  "offset": 50
                },
                {
                  "val": "\"21/05/2022\"",
                  "offset": 55
                },
                {
                  "val": "\"28/05/2022\"",
                  "offset": 69
                },
                {
                  "val": "\"4\"",
                  "offset": 83
                },
                {
                  "val": "\"1\"",
                  "offset": 91
                }
              ],
              "location": "StepDef.user_select_and(String,String,String,String,String,String,String,String)"
            },
            "keyword": "When "
          },
          {
            "result": {
              "duration": 1004800900,
              "status": "passed"
            },
            "line": 13,
            "name": "user should click search button",
            "match": {
              "location": "StepDef.user_should_click_search_button()"
            },
            "keyword": "And "
          },
          {
            "result": {
              "duration": 964614800,
              "status": "passed"
            },
            "line": 15,
            "name": "user select hotel and click continue for booking",
            "match": {
              "location": "StepDef.user_select_hotel_and_click_continue_for_booking()"
            },
            "keyword": "When "
          },
          {
            "result": {
              "duration": 1470259500,
              "status": "passed"
            },
            "line": 17,
            "name": "user enter \"Mohan\", \"Kumar\", \"Chennai,Tamilnadu\", \"4563984512988765\",  \"VISA\", \"8\", \"2022\", \"240\"",
            "match": {
              "arguments": [
                {
                  "val": "\"Mohan\"",
                  "offset": 11
                },
                {
                  "val": "\"Kumar\"",
                  "offset": 20
                },
                {
                  "val": "\"Chennai,Tamilnadu\"",
                  "offset": 29
                },
                {
                  "val": "\"4563984512988765\"",
                  "offset": 50
                },
                {
                  "val": "\"VISA\"",
                  "offset": 71
                },
                {
                  "val": "\"8\"",
                  "offset": 79
                },
                {
                  "val": "\"2022\"",
                  "offset": 84
                },
                {
                  "val": "\"240\"",
                  "offset": 92
                }
              ],
              "location": "StepDef.user_enter(String,String,String,String,String,String,String,String)"
            },
            "keyword": "When "
          },
          {
            "result": {
              "duration": 119696300,
              "status": "passed"
            },
            "line": 19,
            "name": "user click on continue for generating order id",
            "match": {
              "location": "StepDef.user_click_on_continue_for_generating_order_id()"
            },
            "keyword": "And "
          },
          {
            "result": {
              "duration": 5781171100,
              "status": "passed"
            },
            "line": 21,
            "name": "user print order id into console",
            "match": {
              "location": "StepDef.user_print_order_id_into_console()"
            },
            "keyword": "And "
          }
        ]
      },
      {
        "line": 32,
        "name": "Generating order id",
        "description": "",
        "id": "generating-10-order-id-from-adactin-hotel-page;generating-order-id;;5",
        "type": "scenario",
        "keyword": "Scenario Outline",
        "steps": [
          {
            "result": {
              "duration": 13900159500,
              "status": "passed"
            },
            "line": 5,
            "name": "user is on adactin application on chrome browser",
            "match": {
              "location": "StepDef.user_is_on_adactin_application_on_chrome_browser()"
            },
            "keyword": "Given "
          },
          {
            "result": {
              "duration": 497349900,
              "status": "passed"
            },
            "line": 7,
            "name": "user enter \"mohankumar08\" and \"Mohan@123\"",
            "match": {
              "arguments": [
                {
                  "val": "\"mohankumar08\"",
                  "offset": 11
                },
                {
                  "val": "\"Mohan@123\"",
                  "offset": 30
                }
              ],
              "location": "StepDef.user_enter_and(String,String)"
            },
            "keyword": "When "
          },
          {
            "result": {
              "duration": 2722913200,
              "status": "passed"
            },
            "line": 9,
            "name": "user should click login button",
            "match": {
              "location": "StepDef.user_should_click_login_button()"
            },
            "keyword": "And "
          },
          {
            "result": {
              "duration": 1155112000,
              "status": "passed"
            },
            "line": 11,
            "name": "user select \"New York\", \"Hotel Cornice\", \"Deluxe\", \"4\", \"08/05/2022\", \"12/05/2022\", \"3\" and \"1\"",
            "match": {
              "arguments": [
                {
                  "val": "\"New York\"",
                  "offset": 12
                },
                {
                  "val": "\"Hotel Cornice\"",
                  "offset": 24
                },
                {
                  "val": "\"Deluxe\"",
                  "offset": 41
                },
                {
                  "val": "\"4\"",
                  "offset": 51
                },
                {
                  "val": "\"08/05/2022\"",
                  "offset": 56
                },
                {
                  "val": "\"12/05/2022\"",
                  "offset": 70
                },
                {
                  "val": "\"3\"",
                  "offset": 84
                },
                {
                  "val": "\"1\"",
                  "offset": 92
                }
              ],
              "location": "StepDef.user_select_and(String,String,String,String,String,String,String,String)"
            },
            "keyword": "When "
          },
          {
            "result": {
              "duration": 1051155200,
              "status": "passed"
            },
            "line": 13,
            "name": "user should click search button",
            "match": {
              "location": "StepDef.user_should_click_search_button()"
            },
            "keyword": "And "
          },
          {
            "result": {
              "duration": 1051190300,
              "status": "passed"
            },
            "line": 15,
            "name": "user select hotel and click continue for booking",
            "match": {
              "location": "StepDef.user_select_hotel_and_click_continue_for_booking()"
            },
            "keyword": "When "
          },
          {
            "result": {
              "duration": 1827093800,
              "status": "passed"
            },
            "line": 17,
            "name": "user enter \"Mohan\", \"Kumar\", \"Chennai,Tamilnadu\", \"4563984512988765\",  \"VISA\", \"8\", \"2022\", \"240\"",
            "match": {
              "arguments": [
                {
                  "val": "\"Mohan\"",
                  "offset": 11
                },
                {
                  "val": "\"Kumar\"",
                  "offset": 20
                },
                {
                  "val": "\"Chennai,Tamilnadu\"",
                  "offset": 29
                },
                {
                  "val": "\"4563984512988765\"",
                  "offset": 50
                },
                {
                  "val": "\"VISA\"",
                  "offset": 71
                },
                {
                  "val": "\"8\"",
                  "offset": 79
                },
                {
                  "val": "\"2022\"",
                  "offset": 84
                },
                {
                  "val": "\"240\"",
                  "offset": 92
                }
              ],
              "location": "StepDef.user_enter(String,String,String,String,String,String,String,String)"
            },
            "keyword": "When "
          },
          {
            "result": {
              "duration": 141699900,
              "status": "passed"
            },
            "line": 19,
            "name": "user click on continue for generating order id",
            "match": {
              "location": "StepDef.user_click_on_continue_for_generating_order_id()"
            },
            "keyword": "And "
          },
          {
            "result": {
              "duration": 7685588500,
              "status": "passed"
            },
            "line": 21,
            "name": "user print order id into console",
            "match": {
              "location": "StepDef.user_print_order_id_into_console()"
            },
            "keyword": "And "
          }
        ]
      },
      {
        "line": 34,
        "name": "Generating order id",
        "description": "",
        "id": "generating-10-order-id-from-adactin-hotel-page;generating-order-id;;6",
        "type": "scenario",
        "keyword": "Scenario Outline",
        "steps": [
          {
            "result": {
              "duration": 21748378000,
              "status": "passed"
            },
            "line": 5,
            "name": "user is on adactin application on chrome browser",
            "match": {
              "location": "StepDef.user_is_on_adactin_application_on_chrome_browser()"
            },
            "keyword": "Given "
          },
          {
            "result": {
              "duration": 750044100,
              "status": "passed"
            },
            "line": 7,
            "name": "user enter \"mohankumar08\" and \"Mohan@123\"",
            "match": {
              "arguments": [
                {
                  "val": "\"mohankumar08\"",
                  "offset": 11
                },
                {
                  "val": "\"Mohan@123\"",
                  "offset": 30
                }
              ],
              "location": "StepDef.user_enter_and(String,String)"
            },
            "keyword": "When "
          },
          {
            "result": {
              "duration": 2639359600,
              "status": "passed"
            },
            "line": 9,
            "name": "user should click login button",
            "match": {
              "location": "StepDef.user_should_click_login_button()"
            },
            "keyword": "And "
          },
          {
            "result": {
              "duration": 1685832400,
              "status": "passed"
            },
            "line": 11,
            "name": "user select \"Paris\", \"Hotel Creek\", \"Standard\", \"2\", \"18/05/2022\", \"25/05/2022\", \"4\" and \"1\"",
            "match": {
              "arguments": [
                {
                  "val": "\"Paris\"",
                  "offset": 12
                },
                {
                  "val": "\"Hotel Creek\"",
                  "offset": 21
                },
                {
                  "val": "\"Standard\"",
                  "offset": 36
                },
                {
                  "val": "\"2\"",
                  "offset": 48
                },
                {
                  "val": "\"18/05/2022\"",
                  "offset": 53
                },
                {
                  "val": "\"25/05/2022\"",
                  "offset": 67
                },
                {
                  "val": "\"4\"",
                  "offset": 81
                },
                {
                  "val": "\"1\"",
                  "offset": 89
                }
              ],
              "location": "StepDef.user_select_and(String,String,String,String,String,String,String,String)"
            },
            "keyword": "When "
          },
          {
            "result": {
              "duration": 1606611500,
              "status": "passed"
            },
            "line": 13,
            "name": "user should click search button",
            "match": {
              "location": "StepDef.user_should_click_search_button()"
            },
            "keyword": "And "
          },
          {
            "result": {
              "duration": 1363896800,
              "status": "passed"
            },
            "line": 15,
            "name": "user select hotel and click continue for booking",
            "match": {
              "location": "StepDef.user_select_hotel_and_click_continue_for_booking()"
            },
            "keyword": "When "
          },
          {
            "result": {
              "duration": 1554021800,
              "status": "passed"
            },
            "line": 17,
            "name": "user enter \"Mohan\", \"Kumar\", \"Chennai,Tamilnadu\", \"4563984512988765\",  \"VISA\", \"8\", \"2022\", \"240\"",
            "match": {
              "arguments": [
                {
                  "val": "\"Mohan\"",
                  "offset": 11
                },
                {
                  "val": "\"Kumar\"",
                  "offset": 20
                },
                {
                  "val": "\"Chennai,Tamilnadu\"",
                  "offset": 29
                },
                {
                  "val": "\"4563984512988765\"",
                  "offset": 50
                },
                {
                  "val": "\"VISA\"",
                  "offset": 71
                },
                {
                  "val": "\"8\"",
                  "offset": 79
                },
                {
                  "val": "\"2022\"",
                  "offset": 84
                },
                {
                  "val": "\"240\"",
                  "offset": 92
                }
              ],
              "location": "StepDef.user_enter(String,String,String,String,String,String,String,String)"
            },
            "keyword": "When "
          },
          {
            "result": {
              "duration": 94779700,
              "status": "passed"
            },
            "line": 19,
            "name": "user click on continue for generating order id",
            "match": {
              "location": "StepDef.user_click_on_continue_for_generating_order_id()"
            },
            "keyword": "And "
          },
          {
            "result": {
              "duration": 5845753800,
              "status": "passed"
            },
            "line": 21,
            "name": "user print order id into console",
            "match": {
              "location": "StepDef.user_print_order_id_into_console()"
            },
            "keyword": "And "
          }
        ]
      },
      {
        "line": 36,
        "name": "Generating order id",
        "description": "",
        "id": "generating-10-order-id-from-adactin-hotel-page;generating-order-id;;7",
        "type": "scenario",
        "keyword": "Scenario Outline",
        "steps": [
          {
            "result": {
              "duration": 15933642300,
              "status": "passed"
            },
            "line": 5,
            "name": "user is on adactin application on chrome browser",
            "match": {
              "location": "StepDef.user_is_on_adactin_application_on_chrome_browser()"
            },
            "keyword": "Given "
          },
          {
            "result": {
              "duration": 593339100,
              "status": "passed"
            },
            "line": 7,
            "name": "user enter \"mohankumar08\" and \"Mohan@123\"",
            "match": {
              "arguments": [
                {
                  "val": "\"mohankumar08\"",
                  "offset": 11
                },
                {
                  "val": "\"Mohan@123\"",
                  "offset": 30
                }
              ],
              "location": "StepDef.user_enter_and(String,String)"
            },
            "keyword": "When "
          },
          {
            "result": {
              "duration": 2963283800,
              "status": "passed"
            },
            "line": 9,
            "name": "user should click login button",
            "match": {
              "location": "StepDef.user_should_click_login_button()"
            },
            "keyword": "And "
          },
          {
            "result": {
              "duration": 922303100,
              "status": "passed"
            },
            "line": 11,
            "name": "user select \"Sydney\", \"Hotel Hervey\", \"Double\", \"5\", \"12/05/2022\", \"18/05/2022\", \"1\" and \"1\"",
            "match": {
              "arguments": [
                {
                  "val": "\"Sydney\"",
                  "offset": 12
                },
                {
                  "val": "\"Hotel Hervey\"",
                  "offset": 22
                },
                {
                  "val": "\"Double\"",
                  "offset": 38
                },
                {
                  "val": "\"5\"",
                  "offset": 48
                },
                {
                  "val": "\"12/05/2022\"",
                  "offset": 53
                },
                {
                  "val": "\"18/05/2022\"",
                  "offset": 67
                },
                {
                  "val": "\"1\"",
                  "offset": 81
                },
                {
                  "val": "\"1\"",
                  "offset": 89
                }
              ],
              "location": "StepDef.user_select_and(String,String,String,String,String,String,String,String)"
            },
            "keyword": "When "
          },
          {
            "result": {
              "duration": 1091870400,
              "status": "passed"
            },
            "line": 13,
            "name": "user should click search button",
            "match": {
              "location": "StepDef.user_should_click_search_button()"
            },
            "keyword": "And "
          },
          {
            "result": {
              "duration": 969886200,
              "status": "passed"
            },
            "line": 15,
            "name": "user select hotel and click continue for booking",
            "match": {
              "location": "StepDef.user_select_hotel_and_click_continue_for_booking()"
            },
            "keyword": "When "
          },
          {
            "result": {
              "duration": 1410941900,
              "status": "passed"
            },
            "line": 17,
            "name": "user enter \"Mohan\", \"Kumar\", \"Chennai,Tamilnadu\", \"4563984512988765\",  \"VISA\", \"8\", \"2022\", \"240\"",
            "match": {
              "arguments": [
                {
                  "val": "\"Mohan\"",
                  "offset": 11
                },
                {
                  "val": "\"Kumar\"",
                  "offset": 20
                },
                {
                  "val": "\"Chennai,Tamilnadu\"",
                  "offset": 29
                },
                {
                  "val": "\"4563984512988765\"",
                  "offset": 50
                },
                {
                  "val": "\"VISA\"",
                  "offset": 71
                },
                {
                  "val": "\"8\"",
                  "offset": 79
                },
                {
                  "val": "\"2022\"",
                  "offset": 84
                },
                {
                  "val": "\"240\"",
                  "offset": 92
                }
              ],
              "location": "StepDef.user_enter(String,String,String,String,String,String,String,String)"
            },
            "keyword": "When "
          },
          {
            "result": {
              "duration": 101589500,
              "status": "passed"
            },
            "line": 19,
            "name": "user click on continue for generating order id",
            "match": {
              "location": "StepDef.user_click_on_continue_for_generating_order_id()"
            },
            "keyword": "And "
          },
          {
            "result": {
              "duration": 5950233500,
              "status": "passed"
            },
            "line": 21,
            "name": "user print order id into console",
            "match": {
              "location": "StepDef.user_print_order_id_into_console()"
            },
            "keyword": "And "
          }
        ]
      },
      {
        "line": 38,
        "name": "Generating order id",
        "description": "",
        "id": "generating-10-order-id-from-adactin-hotel-page;generating-order-id;;8",
        "type": "scenario",
        "keyword": "Scenario Outline",
        "steps": [
          {
            "result": {
              "duration": 63176368300,
              "status": "passed"
            },
            "line": 5,
            "name": "user is on adactin application on chrome browser",
            "match": {
              "location": "StepDef.user_is_on_adactin_application_on_chrome_browser()"
            },
            "keyword": "Given "
          },
          {
            "result": {
              "duration": 593949600,
              "status": "passed"
            },
            "line": 7,
            "name": "user enter \"mohankumar08\" and \"Mohan@123\"",
            "match": {
              "arguments": [
                {
                  "val": "\"mohankumar08\"",
                  "offset": 11
                },
                {
                  "val": "\"Mohan@123\"",
                  "offset": 30
                }
              ],
              "location": "StepDef.user_enter_and(String,String)"
            },
            "keyword": "When "
          },
          {
            "result": {
              "duration": 3360706400,
              "status": "passed"
            },
            "line": 9,
            "name": "user should click login button",
            "match": {
              "location": "StepDef.user_should_click_login_button()"
            },
            "keyword": "And "
          },
          {
            "result": {
              "duration": 1382755300,
              "status": "passed"
            },
            "line": 11,
            "name": "user select \"Melbourne\", \"Hotel Sunshine\", \"Super Deluxe\", \"3\", \"26/05/2022\", \"28/05/2022\", \"4\" and \"1\"",
            "match": {
              "arguments": [
                {
                  "val": "\"Melbourne\"",
                  "offset": 12
                },
                {
                  "val": "\"Hotel Sunshine\"",
                  "offset": 25
                },
                {
                  "val": "\"Super Deluxe\"",
                  "offset": 43
                },
                {
                  "val": "\"3\"",
                  "offset": 59
                },
                {
                  "val": "\"26/05/2022\"",
                  "offset": 64
                },
                {
                  "val": "\"28/05/2022\"",
                  "offset": 78
                },
                {
                  "val": "\"4\"",
                  "offset": 92
                },
                {
                  "val": "\"1\"",
                  "offset": 100
                }
              ],
              "location": "StepDef.user_select_and(String,String,String,String,String,String,String,String)"
            },
            "keyword": "When "
          },
          {
            "result": {
              "duration": 1083349800,
              "status": "passed"
            },
            "line": 13,
            "name": "user should click search button",
            "match": {
              "location": "StepDef.user_should_click_search_button()"
            },
            "keyword": "And "
          },
          {
            "result": {
              "duration": 999357300,
              "status": "passed"
            },
            "line": 15,
            "name": "user select hotel and click continue for booking",
            "match": {
              "location": "StepDef.user_select_hotel_and_click_continue_for_booking()"
            },
            "keyword": "When "
          },
          {
            "result": {
              "duration": 1487303300,
              "status": "passed"
            },
            "line": 17,
            "name": "user enter \"Mohan\", \"Kumar\", \"Chennai,Tamilnadu\", \"4563984512988765\",  \"VISA\", \"8\", \"2022\", \"240\"",
            "match": {
              "arguments": [
                {
                  "val": "\"Mohan\"",
                  "offset": 11
                },
                {
                  "val": "\"Kumar\"",
                  "offset": 20
                },
                {
                  "val": "\"Chennai,Tamilnadu\"",
                  "offset": 29
                },
                {
                  "val": "\"4563984512988765\"",
                  "offset": 50
                },
                {
                  "val": "\"VISA\"",
                  "offset": 71
                },
                {
                  "val": "\"8\"",
                  "offset": 79
                },
                {
                  "val": "\"2022\"",
                  "offset": 84
                },
                {
                  "val": "\"240\"",
                  "offset": 92
                }
              ],
              "location": "StepDef.user_enter(String,String,String,String,String,String,String,String)"
            },
            "keyword": "When "
          },
          {
            "result": {
              "duration": 95424200,
              "status": "passed"
            },
            "line": 19,
            "name": "user click on continue for generating order id",
            "match": {
              "location": "StepDef.user_click_on_continue_for_generating_order_id()"
            },
            "keyword": "And "
          },
          {
            "result": {
              "duration": 6353996900,
              "status": "passed"
            },
            "line": 21,
            "name": "user print order id into console",
            "match": {
              "location": "StepDef.user_print_order_id_into_console()"
            },
            "keyword": "And "
          }
        ]
      },
      {
        "line": 40,
        "name": "Generating order id",
        "description": "",
        "id": "generating-10-order-id-from-adactin-hotel-page;generating-order-id;;9",
        "type": "scenario",
        "keyword": "Scenario Outline",
        "steps": [
          {
            "result": {
              "duration": 23605539200,
              "status": "passed"
            },
            "line": 5,
            "name": "user is on adactin application on chrome browser",
            "match": {
              "location": "StepDef.user_is_on_adactin_application_on_chrome_browser()"
            },
            "keyword": "Given "
          },
          {
            "result": {
              "duration": 1202076800,
              "status": "passed"
            },
            "line": 7,
            "name": "user enter \"mohankumar08\" and \"Mohan@123\"",
            "match": {
              "arguments": [
                {
                  "val": "\"mohankumar08\"",
                  "offset": 11
                },
                {
                  "val": "\"Mohan@123\"",
                  "offset": 30
                }
              ],
              "location": "StepDef.user_enter_and(String,String)"
            },
            "keyword": "When "
          },
          {
            "result": {
              "duration": 2723930900,
              "status": "passed"
            },
            "line": 9,
            "name": "user should click login button",
            "match": {
              "location": "StepDef.user_should_click_login_button()"
            },
            "keyword": "And "
          },
          {
            "result": {
              "duration": 1451449300,
              "status": "passed"
            },
            "line": 11,
            "name": "user select \"Brisbane\", \"Hotel Creek\", \"Standard\", \"6\", \"08/05/2022\", \"12/05/2022\", \"3\" and \"1\"",
            "match": {
              "arguments": [
                {
                  "val": "\"Brisbane\"",
                  "offset": 12
                },
                {
                  "val": "\"Hotel Creek\"",
                  "offset": 24
                },
                {
                  "val": "\"Standard\"",
                  "offset": 39
                },
                {
                  "val": "\"6\"",
                  "offset": 51
                },
                {
                  "val": "\"08/05/2022\"",
                  "offset": 56
                },
                {
                  "val": "\"12/05/2022\"",
                  "offset": 70
                },
                {
                  "val": "\"3\"",
                  "offset": 84
                },
                {
                  "val": "\"1\"",
                  "offset": 92
                }
              ],
              "location": "StepDef.user_select_and(String,String,String,String,String,String,String,String)"
            },
            "keyword": "When "
          },
          {
            "result": {
              "duration": 1088174100,
              "status": "passed"
            },
            "line": 13,
            "name": "user should click search button",
            "match": {
              "location": "StepDef.user_should_click_search_button()"
            },
            "keyword": "And "
          },
          {
            "result": {
              "duration": 1583505200,
              "status": "passed"
            },
            "line": 15,
            "name": "user select hotel and click continue for booking",
            "match": {
              "location": "StepDef.user_select_hotel_and_click_continue_for_booking()"
            },
            "keyword": "When "
          },
          {
            "result": {
              "duration": 1916812100,
              "status": "passed"
            },
            "line": 17,
            "name": "user enter \"Mohan\", \"Kumar\", \"Chennai,Tamilnadu\", \"4563984512988765\",  \"VISA\", \"8\", \"2022\", \"240\"",
            "match": {
              "arguments": [
                {
                  "val": "\"Mohan\"",
                  "offset": 11
                },
                {
                  "val": "\"Kumar\"",
                  "offset": 20
                },
                {
                  "val": "\"Chennai,Tamilnadu\"",
                  "offset": 29
                },
                {
                  "val": "\"4563984512988765\"",
                  "offset": 50
                },
                {
                  "val": "\"VISA\"",
                  "offset": 71
                },
                {
                  "val": "\"8\"",
                  "offset": 79
                },
                {
                  "val": "\"2022\"",
                  "offset": 84
                },
                {
                  "val": "\"240\"",
                  "offset": 92
                }
              ],
              "location": "StepDef.user_enter(String,String,String,String,String,String,String,String)"
            },
            "keyword": "When "
          },
          {
            "result": {
              "duration": 111484200,
              "status": "passed"
            },
            "line": 19,
            "name": "user click on continue for generating order id",
            "match": {
              "location": "StepDef.user_click_on_continue_for_generating_order_id()"
            },
            "keyword": "And "
          },
          {
            "result": {
              "duration": 6131905100,
              "status": "passed"
            },
            "line": 21,
            "name": "user print order id into console",
            "match": {
              "location": "StepDef.user_print_order_id_into_console()"
            },
            "keyword": "And "
          }
        ]
      },
      {
        "line": 42,
        "name": "Generating order id",
        "description": "",
        "id": "generating-10-order-id-from-adactin-hotel-page;generating-order-id;;10",
        "type": "scenario",
        "keyword": "Scenario Outline",
        "steps": [
          {
            "result": {
              "duration": 26635756000,
              "status": "passed"
            },
            "line": 5,
            "name": "user is on adactin application on chrome browser",
            "match": {
              "location": "StepDef.user_is_on_adactin_application_on_chrome_browser()"
            },
            "keyword": "Given "
          },
          {
            "result": {
              "duration": 490214900,
              "status": "passed"
            },
            "line": 7,
            "name": "user enter \"mohankumar08\" and \"Mohan@123\"",
            "match": {
              "arguments": [
                {
                  "val": "\"mohankumar08\"",
                  "offset": 11
                },
                {
                  "val": "\"Mohan@123\"",
                  "offset": 30
                }
              ],
              "location": "StepDef.user_enter_and(String,String)"
            },
            "keyword": "When "
          },
          {
            "result": {
              "duration": 2557704500,
              "status": "passed"
            },
            "line": 9,
            "name": "user should click login button",
            "match": {
              "location": "StepDef.user_should_click_login_button()"
            },
            "keyword": "And "
          },
          {
            "result": {
              "duration": 1253327600,
              "status": "passed"
            },
            "line": 11,
            "name": "user select \"New York\", \"Hotel Hervey\", \"Super Deluxe\", \"2\", \"18/05/2022\", \"20/05/2022\", \"2\" and \"1\"",
            "match": {
              "arguments": [
                {
                  "val": "\"New York\"",
                  "offset": 12
                },
                {
                  "val": "\"Hotel Hervey\"",
                  "offset": 24
                },
                {
                  "val": "\"Super Deluxe\"",
                  "offset": 40
                },
                {
                  "val": "\"2\"",
                  "offset": 56
                },
                {
                  "val": "\"18/05/2022\"",
                  "offset": 61
                },
                {
                  "val": "\"20/05/2022\"",
                  "offset": 75
                },
                {
                  "val": "\"2\"",
                  "offset": 89
                },
                {
                  "val": "\"1\"",
                  "offset": 97
                }
              ],
              "location": "StepDef.user_select_and(String,String,String,String,String,String,String,String)"
            },
            "keyword": "When "
          },
          {
            "result": {
              "duration": 1109740300,
              "status": "passed"
            },
            "line": 13,
            "name": "user should click search button",
            "match": {
              "location": "StepDef.user_should_click_search_button()"
            },
            "keyword": "And "
          },
          {
            "result": {
              "duration": 1415385000,
              "status": "passed"
            },
            "line": 15,
            "name": "user select hotel and click continue for booking",
            "match": {
              "location": "StepDef.user_select_hotel_and_click_continue_for_booking()"
            },
            "keyword": "When "
          },
          {
            "result": {
              "duration": 1805775800,
              "status": "passed"
            },
            "line": 17,
            "name": "user enter \"Mohan\", \"Kumar\", \"Chennai,Tamilnadu\", \"4563984512988765\",  \"VISA\", \"8\", \"2022\", \"240\"",
            "match": {
              "arguments": [
                {
                  "val": "\"Mohan\"",
                  "offset": 11
                },
                {
                  "val": "\"Kumar\"",
                  "offset": 20
                },
                {
                  "val": "\"Chennai,Tamilnadu\"",
                  "offset": 29
                },
                {
                  "val": "\"4563984512988765\"",
                  "offset": 50
                },
                {
                  "val": "\"VISA\"",
                  "offset": 71
                },
                {
                  "val": "\"8\"",
                  "offset": 79
                },
                {
                  "val": "\"2022\"",
                  "offset": 84
                },
                {
                  "val": "\"240\"",
                  "offset": 92
                }
              ],
              "location": "StepDef.user_enter(String,String,String,String,String,String,String,String)"
            },
            "keyword": "When "
          },
          {
            "result": {
              "duration": 114215600,
              "status": "passed"
            },
            "line": 19,
            "name": "user click on continue for generating order id",
            "match": {
              "location": "StepDef.user_click_on_continue_for_generating_order_id()"
            },
            "keyword": "And "
          },
          {
            "result": {
              "duration": 6069496300,
              "status": "passed"
            },
            "line": 21,
            "name": "user print order id into console",
            "match": {
              "location": "StepDef.user_print_order_id_into_console()"
            },
            "keyword": "And "
          }
        ]
      },
      {
        "line": 44,
        "name": "Generating order id",
        "description": "",
        "id": "generating-10-order-id-from-adactin-hotel-page;generating-order-id;;11",
        "type": "scenario",
        "keyword": "Scenario Outline",
        "steps": [
          {
            "result": {
              "duration": 27737036200,
              "status": "passed"
            },
            "line": 5,
            "name": "user is on adactin application on chrome browser",
            "match": {
              "location": "StepDef.user_is_on_adactin_application_on_chrome_browser()"
            },
            "keyword": "Given "
          },
          {
            "result": {
              "duration": 499006000,
              "status": "passed"
            },
            "line": 7,
            "name": "user enter \"mohankumar08\" and \"Mohan@123\"",
            "match": {
              "arguments": [
                {
                  "val": "\"mohankumar08\"",
                  "offset": 11
                },
                {
                  "val": "\"Mohan@123\"",
                  "offset": 30
                }
              ],
              "location": "StepDef.user_enter_and(String,String)"
            },
            "keyword": "When "
          },
          {
            "result": {
              "duration": 3017785000,
              "status": "passed"
            },
            "line": 9,
            "name": "user should click login button",
            "match": {
              "location": "StepDef.user_should_click_login_button()"
            },
            "keyword": "And "
          },
          {
            "result": {
              "duration": 1422325400,
              "status": "passed"
            },
            "line": 11,
            "name": "user select \"Paris\", \"Hotel Creek\", \"Double\", \"1\", \"21/05/2022\", \"24/05/2022\", \"4\" and \"1\"",
            "match": {
              "arguments": [
                {
                  "val": "\"Paris\"",
                  "offset": 12
                },
                {
                  "val": "\"Hotel Creek\"",
                  "offset": 21
                },
                {
                  "val": "\"Double\"",
                  "offset": 36
                },
                {
                  "val": "\"1\"",
                  "offset": 46
                },
                {
                  "val": "\"21/05/2022\"",
                  "offset": 51
                },
                {
                  "val": "\"24/05/2022\"",
                  "offset": 65
                },
                {
                  "val": "\"4\"",
                  "offset": 79
                },
                {
                  "val": "\"1\"",
                  "offset": 87
                }
              ],
              "location": "StepDef.user_select_and(String,String,String,String,String,String,String,String)"
            },
            "keyword": "When "
          },
          {
            "result": {
              "duration": 1069781600,
              "status": "passed"
            },
            "line": 13,
            "name": "user should click search button",
            "match": {
              "location": "StepDef.user_should_click_search_button()"
            },
            "keyword": "And "
          },
          {
            "result": {
              "duration": 1038849800,
              "status": "passed"
            },
            "line": 15,
            "name": "user select hotel and click continue for booking",
            "match": {
              "location": "StepDef.user_select_hotel_and_click_continue_for_booking()"
            },
            "keyword": "When "
          },
          {
            "result": {
              "duration": 1948713600,
              "status": "passed"
            },
            "line": 17,
            "name": "user enter \"Mohan\", \"Kumar\", \"Chennai,Tamilnadu\", \"4563984512988765\",  \"VISA\", \"8\", \"2022\", \"240\"",
            "match": {
              "arguments": [
                {
                  "val": "\"Mohan\"",
                  "offset": 11
                },
                {
                  "val": "\"Kumar\"",
                  "offset": 20
                },
                {
                  "val": "\"Chennai,Tamilnadu\"",
                  "offset": 29
                },
                {
                  "val": "\"4563984512988765\"",
                  "offset": 50
                },
                {
                  "val": "\"VISA\"",
                  "offset": 71
                },
                {
                  "val": "\"8\"",
                  "offset": 79
                },
                {
                  "val": "\"2022\"",
                  "offset": 84
                },
                {
                  "val": "\"240\"",
                  "offset": 92
                }
              ],
              "location": "StepDef.user_enter(String,String,String,String,String,String,String,String)"
            },
            "keyword": "When "
          },
          {
            "result": {
              "duration": 153732900,
              "status": "passed"
            },
            "line": 19,
            "name": "user click on continue for generating order id",
            "match": {
              "location": "StepDef.user_click_on_continue_for_generating_order_id()"
            },
            "keyword": "And "
          },
          {
            "result": {
              "duration": 6097186800,
              "status": "passed"
            },
            "line": 21,
            "name": "user print order id into console",
            "match": {
              "location": "StepDef.user_print_order_id_into_console()"
            },
            "keyword": "And "
          }
        ]
      }
    ],
    "name": "Generating 10 order id from adactin hotel page",
    "description": "",
    "id": "generating-10-order-id-from-adactin-hotel-page",
    "keyword": "Feature",
    "uri": "src/test/resources/Login.feature",
    "tags": []
  }
]